contatos/__init__.py
contatos/conexao.py
contatos/contato.py
contatos/main.py
contatos/pessoa.py
contatos/sistema.py
models/__init__.py
models/conexao.py
models/contato.py
models/main.py
models/pessoa.py
models/sistema.py
contatos-0.0.1.dist-info/METADATA
contatos-0.0.1.dist-info/WHEEL
contatos-0.0.1.dist-info/top_level.txt
contatos-0.0.1.dist-info/RECORD
