Metadata-Version: 2.1
Name: contatos
Version: 0.0.1
Summary: sistema de contato
Home-page: https://github.com/ubiratantavares/projeto_sistema_contato
Author: Ubiratan Tavares
Author-email: ust1973@gmail.com
Requires-Python: >=3.9
Requires-Dist: mysql-connector-python
